pulsefire/__init__.py
pulsefire/schemas.py
pulsefire_types-2.0.30.dist-info/licenses/LICENSE
pulsefire_types-2.0.30.dist-info/METADATA
pulsefire_types-2.0.30.dist-info/WHEEL
pulsefire_types-2.0.30.dist-info/top_level.txt
pulsefire_types-2.0.30.dist-info/zip-safe
pulsefire_types-2.0.30.dist-info/RECORD
