Metadata-Version: 2.4
Name: pulsefire-types
Version: 2.0.30
Summary: A modern and flexible Riot Games Python SDK.
Home-page: https://github.com/ianhco/pulsefire
Author: Ian Huang
License: MIT
Keywords: Riot Games,League of Legends,Teamfight Tactics,Valorant,Legends of Runeterra,API,SDK,asyncio
Classifier: Development Status :: 5 - Production/Stable
Classifier: Programming Language :: Python :: 3.12
Classifier: Environment :: Web Environment
Classifier: Operating System :: OS Independent
Classifier: Intended Audience :: Developers
Classifier: License :: OSI Approved :: MIT License
Classifier: Topic :: Games/Entertainment
Classifier: Topic :: Software Development :: Libraries :: Python Modules
Classifier: Natural Language :: English
License-File: LICENSE
Dynamic: author
Dynamic: classifier
Dynamic: description
Dynamic: description-content-type
Dynamic: home-page
Dynamic: keywords
Dynamic: license
Dynamic: license-file
Dynamic: summary
